Metadata-Version: 2.1
Name: discord-passport
Version: 0.2
Summary: discord-passport is easier way to create simple Oauth with Discord-API
Home-page: UNKNOWN
Author: Zaid Ali
Author-email: email@iexi.xyz
License: MIT
Keywords: discord,api,oauth
Platform: UNKNOWN
Classifier: Development Status :: 1 - Planning
Classifier: Intended Audience :: Developers
Classifier: Programming Language :: Python :: 3
Classifier: Operating System :: Unix
Classifier: Operating System :: MacOS :: MacOS X
Classifier: Operating System :: Microsoft :: Windows
